iohinspector/__init__.py
iohinspector/align.py
iohinspector/data.py
iohinspector/manager.py
iohinspector/indicators/__init__.py
iohinspector/indicators/anytime.py
iohinspector/indicators/final.py
iohinspector/metrics/__init__.py
iohinspector/metrics/aocc.py
iohinspector/metrics/attractor_network.py
iohinspector/metrics/eaf.py
iohinspector/metrics/ecdf.py
iohinspector/metrics/fixed_budget.py
iohinspector/metrics/fixed_target.py
iohinspector/metrics/multi_objective.py
iohinspector/metrics/ranking.py
iohinspector/metrics/single_run.py
iohinspector/metrics/trajectory.py
iohinspector/metrics/utils.py
iohinspector/plots/__init__.py
iohinspector/plots/attractor_network.py
iohinspector/plots/eaf.py
iohinspector/plots/ecdf.py
iohinspector/plots/fixed_budget.py
iohinspector/plots/fixed_target.py
iohinspector/plots/multi_objective.py
iohinspector/plots/ranking.py
iohinspector/plots/single_run.py
iohinspector/plots/utils.py
iohinspector-0.0.6.dist-info/METADATA
iohinspector-0.0.6.dist-info/WHEEL
iohinspector-0.0.6.dist-info/top_level.txt
iohinspector-0.0.6.dist-info/RECORD
