Metadata-Version: 2.4
Name: iohinspector
Version: 0.0.6
Summary: Package for managing IOH data
Author-email: Diederick Vermetten <d.vermetten@gmail.com>, Jacob de Nobel <jacobdenobel@gmail.com>
Project-URL: Homepage, https://github.com/IOHprofiler/iohinspector
Project-URL: Issues, https://github.com/IOHprofiler/iohinspector/issues
Classifier: Programming Language :: Python :: 3
Classifier: License :: OSI Approved :: MIT License
Classifier: Operating System :: OS Independent
Requires-Python: >=3.8
Requires-Dist: matplotlib
Requires-Dist: moocore>=0.1.8
Requires-Dist: numpy
Requires-Dist: pandas
Requires-Dist: polars>=1.33.1
Requires-Dist: pyarrow
Requires-Dist: robustranking
Requires-Dist: seaborn
Requires-Dist: skelo
Requires-Dist: networkx
Provides-Extra: test
Requires-Dist: coverage; extra == "test"
Requires-Dist: ioh; extra == "test"
Requires-Dist: pymoo; extra == "test"
